asyncslot/__init__.py
asyncslot/_base_events.py
asyncslot/_proactor_events.py
asyncslot/_runners.py
asyncslot/_selectable.py
asyncslot/_selector_events.py
asyncslot/_slot.py
asyncslot/_unix_events.py
asyncslot/_windows_events.py
asyncslot/bindings.py
asyncslot-0.3.1.dist-info/LICENSE
asyncslot-0.3.1.dist-info/METADATA
asyncslot-0.3.1.dist-info/WHEEL
asyncslot-0.3.1.dist-info/top_level.txt
asyncslot-0.3.1.dist-info/RECORD
