Metadata-Version: 2.1
Name: asyncslot
Version: 0.3.1
Summary: Use asyncio-based library from Python for Qt.
Author-email: fancidev <fancidev@gmail.com>
Project-URL: Homepage, https://github.com/fancidev/asyncslot
Project-URL: Bug Tracker, https://github.com/fancidev/asyncslot/issues
Keywords: asyncio,coroutine,qt,signal,slot
Classifier: Development Status :: 2 - Pre-Alpha
Classifier: Environment :: X11 Applications :: Qt
Classifier: Framework :: AsyncIO
Classifier: Intended Audience :: Developers
Classifier: License :: OSI Approved :: BSD License
Classifier: Operating System :: OS Independent
Classifier: Programming Language :: Python :: 3
Requires-Python: >=3.7
License-File: LICENSE
Provides-Extra: pyqt5
Requires-Dist: PyQt5 ; extra == 'pyqt5'
Provides-Extra: pyqt6
Requires-Dist: PyQt6 ; extra == 'pyqt6'
Provides-Extra: pyside2
Requires-Dist: PySide2 ; extra == 'pyside2'
Provides-Extra: pyside6
Requires-Dist: PySide6 ; extra == 'pyside6'
